{
  "workItemId": 100,
  "currentState": "AI Code",
  "createdAt": "2026-02-20T07:08:34.5898065Z",
  "updatedAt": "2026-02-20T07:39:19.3758844Z",
  "agents": {
    "Planning": {
      "status": "in_progress",
      "startedAt": "2026-02-20T07:38:55.3957606Z",
      "completedAt": null,
      "additionalData": null
    },
    "Coding": {
      "status": "in_progress",
      "startedAt": "2026-02-20T07:39:19.2202515Z",
      "completedAt": null,
      "additionalData": null
    },
    "Testing": {
      "status": "skipped",
      "startedAt": null,
      "completedAt": "2026-02-20T07:22:04.9023853Z",
      "additionalData": {
        "reason": "Copilot coding agent already runs tests"
      }
    },
    "Review": {
      "status": "in_progress",
      "startedAt": "2026-02-20T07:22:09.1676136Z",
      "completedAt": null,
      "additionalData": null
    }
  },
  "artifacts": {
    "code": [
      "dashboard/index.html"
    ],
    "tests": [],
    "docs": []
  },
  "decisions": [],
  "questions": [],
  "tokenUsage": {
    "totalInputTokens": 0,
    "totalOutputTokens": 0,
    "totalTokens": 0,
    "totalCost": 0,
    "complexity": "XS",
    "agents": {
      "Coding": {
        "inputTokens": 0,
        "outputTokens": 0,
        "totalTokens": 0,
        "estimatedCost": 0,
        "model": "copilot-coding-agent",
        "callCount": 1
      }
    }
  }
}